{
  "githubRepo": "igwilvs-grimoire",
  "githubToken": "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",
  "githubUserName": "WolfQuery",
  "gardenBaseUrl": "https://igwilvs-grimoire.vercel.app/",
  "prHistory": [],
  "baseTheme": "light",
  "theme": "{\"name\":\"🔔 Chime\",\"author\":\"Ha'ani Whitlock\",\"repo\":\"Bluemoondragon07/chime-theme\",\"screenshot\":\"Chime.png\",\"modes\":[\"dark\",\"light\"],\"cssUrl\":\"https://raw.githubusercontent.com/Bluemoondragon07/chime-theme/HEAD/theme.css\"}",
  "faviconPath": "z_Assets/digital garden/grimoire icon.svg",
  "useFullResolutionImages": false,
  "noteSettingsIsInitialized": true,
  "siteName": "Igwilv's Grimoire",
  "mainLanguage": "en",
  "slugifyEnabled": true,
  "noteIconKey": "dg-note-icon",
  "defaultNoteIcon": "",
  "showNoteIconOnTitle": false,
  "showNoteIconInFileTree": false,
  "showNoteIconOnInternalLink": false,
  "showNoteIconOnBackLink": false,
  "showCreatedTimestamp": false,
  "createdTimestampKey": "",
  "showUpdatedTimestamp": false,
  "updatedTimestampKey": "",
  "timestampFormat": "dd, MMM, yyyy h:mm a",
  "styleSettingsCss": "body.css-settings-manager { } body.theme-light.css-settings-manager { } body.theme-dark.css-settings-manager { }",
  "styleSettingsBodyClasses": "mod-windows is-frameless is-hidden-frameless obsidian-app theme-light show-inline-title show-ribbon show-view-header is-maximized css-settings-manager its-theme sidebar-float-bottom folder-arrow-hidden Heading check-color check-bg wotc-beyond folder-notes-plugin hide-folder-note folder-note-underline folder-note-underline-path fn-whitespace-stop-collapsing version-1-7-2 is-focused",
  "pathRewriteRules": "",
  "customFilters": [],
  "contentClassesKey": "dg-content-classes",
  "defaultNoteSettings": {
    "dgHomeLink": true,
    "dgPassFrontmatter": false,
    "dgShowBacklinks": false,
    "dgShowLocalGraph": false,
    "dgShowInlineTitle": false,
    "dgShowFileTree": false,
    "dgEnableSearch": true,
    "dgShowToc": false,
    "dgLinkPreview": true,
    "dgShowTags": false
  }
}